app.py
apt_check.py
apt_prom_exporter-0.1.2.data/scripts/apt-prom-exporter
apt_prom_exporter-0.1.2.dist-info/LICENSE
apt_prom_exporter-0.1.2.dist-info/METADATA
apt_prom_exporter-0.1.2.dist-info/WHEEL
apt_prom_exporter-0.1.2.dist-info/top_level.txt
apt_prom_exporter-0.1.2.dist-info/RECORD
