Metadata-Version: 2.1
Name: apt-prom-exporter
Version: 0.1.2
Summary: Prometheus exporter for available apt package updates
Home-page: https://github.com/Alpha200/apt-prom-exporter
Author: Daniel Sendzik
Author-email: daniel@sendzik.eu
License: Apache License 2.0
Platform: UNKNOWN
Requires-Dist: prometheus-client
Requires-Dist: apscheduler
